audio_augmentations/__init__.py
audio_augmentations/apply.py
audio_augmentations/compose.py
audio_augmentations/augmentations/__init__.py
audio_augmentations/augmentations/delay.py
audio_augmentations/augmentations/gain.py
audio_augmentations/augmentations/high_low_pass.py
audio_augmentations/augmentations/noise.py
audio_augmentations/augmentations/pitch_shift.py
audio_augmentations/augmentations/polarity_inversion.py
audio_augmentations/augmentations/random_resized_crop.py
audio_augmentations/augmentations/reverb.py
audio_augmentations/augmentations/reverse.py
audio_augmentations-0.1.3.dist-info/METADATA
audio_augmentations-0.1.3.dist-info/WHEEL
audio_augmentations-0.1.3.dist-info/top_level.txt
audio_augmentations-0.1.3.dist-info/RECORD
