Metadata-Version: 2.1
Name: audio-augmentations
Version: 0.1.3
Summary: Audio augmentations library, for audio in the time-domain.
Home-page: https://github.com/spijkervet/audio-augmentations
Author: Janne Spijkervet
Author-email: janne.spijkervet@gmail.com
License: MIT
Platform: UNKNOWN
Classifier: License :: OSI Approved :: MIT License
Classifier: Programming Language :: Python
Classifier: Programming Language :: Python :: 3
Classifier: Programming Language :: Python :: 3.6
Classifier: Programming Language :: Python :: Implementation :: CPython
Classifier: Programming Language :: Python :: Implementation :: PyPy
Requires-Python: >=3.6.0
Requires-Dist: numpy
Requires-Dist: torch
Requires-Dist: torchaudio
Requires-Dist: essentia
